mwpersistence/__init__.py
mwpersistence/errors.py
mwpersistence/mwpersistence.py
mwpersistence/state.py
mwpersistence/token.py
mwpersistence/util.py
mwpersistence/tests/__init__.py
mwpersistence/tests/test_state.py
mwpersistence/tests/test_token.py
mwpersistence/utilities/__init__.py
mwpersistence/utilities/diffs2persistence.py
mwpersistence/utilities/dump2stats.py
mwpersistence/utilities/persistence2stats.py
mwpersistence/utilities/revdocs2stats.py
mwpersistence/utilities/tests/__init__.py
mwpersistence/utilities/tests/test_diffs2persistence.py
mwpersistence/utilities/tests/test_persistence2stats.py
mwpersistence-0.2.4.dist-info/DESCRIPTION.rst
mwpersistence-0.2.4.dist-info/METADATA
mwpersistence-0.2.4.dist-info/RECORD
mwpersistence-0.2.4.dist-info/WHEEL
mwpersistence-0.2.4.dist-info/entry_points.txt
mwpersistence-0.2.4.dist-info/metadata.json
mwpersistence-0.2.4.dist-info/top_level.txt
